muispasswordgen.py
muispasswordgen-1.2.0.dist-info/METADATA
muispasswordgen-1.2.0.dist-info/WHEEL
muispasswordgen-1.2.0.dist-info/top_level.txt
muispasswordgen-1.2.0.dist-info/RECORD
